llm_embed_ollama.py
llm_embed_ollama-0.1.3.dist-info/licenses/LICENSE
llm_embed_ollama-0.1.3.dist-info/METADATA
llm_embed_ollama-0.1.3.dist-info/WHEEL
llm_embed_ollama-0.1.3.dist-info/entry_points.txt
llm_embed_ollama-0.1.3.dist-info/top_level.txt
llm_embed_ollama-0.1.3.dist-info/RECORD
