Metadata-Version: 2.4
Name: llm-embed-ollama
Version: 0.1.3
Summary: Embedding models using Ollama pulled models
Author: Sukhbinder Singh
License: Apache-2.0
Project-URL: Homepage, https://github.com/sukhbinder/llm-embed-ollama
Project-URL: Changelog, https://github.com/sukhbinder/llm-embed-ollama/releases
Project-URL: Issues, https://github.com/sukhbinder/llm-embed-ollama/issues
Project-URL: CI, https://github.com/sukhbinder/llm-embed-ollama/actions
Classifier: License :: OSI Approved :: Apache Software License
License-File: LICENSE
Requires-Dist: llm
Requires-Dist: ollama
Provides-Extra: test
Requires-Dist: pytest; extra == "test"
Dynamic: license-file
